mutaprops/__init__.py
mutaprops/decorators.py
mutaprops/managers.py
mutaprops/mutaprops.py
mutaprops/utils.py
mutaprops/web_ui/index.html
mutaprops/web_ui/dist/base.css
mutaprops/web_ui/dist/bootstrap-toggle.min.css
mutaprops/web_ui/dist/bootstrap-toggle.min.js
mutaprops/web_ui/dist/bootstrap.min.css
mutaprops/web_ui/dist/bootstrap.min.js
mutaprops/web_ui/dist/build.js
mutaprops/web_ui/dist/jquery-3.1.1.min.js
mutaprops/web_ui/dist/logo.png
mutaprops-0.6.5.dist-info/DESCRIPTION.rst
mutaprops-0.6.5.dist-info/METADATA
mutaprops-0.6.5.dist-info/RECORD
mutaprops-0.6.5.dist-info/WHEEL
mutaprops-0.6.5.dist-info/metadata.json
mutaprops-0.6.5.dist-info/top_level.txt
