Metadata-Version: 2.0
Name: mutaprops
Version: 0.6.5
Summary: Simple UI, autogenerated from your classes.
Home-page: https://github.com/calcite/mutaprops
Author: Josef Nevrly
Author-email: jnevrly@alps.cz
License: MIT license
Keywords: mutaprops,GUI,HTML5,autogenerated
Platform: UNKNOWN
Classifier: Development Status :: 4 - Beta
Classifier: Intended Audience :: Developers
Classifier: Natural Language :: English
Classifier: Programming Language :: Python :: 3.4
Classifier: Programming Language :: Python :: 3.5
Classifier: Programming Language :: Python :: 3.6
Requires-Dist: aiohttp (>=2.3.0)
Requires-Dist: docutils (>=0.13.1)
Requires-Dist: sockjs (==0.6.0)
